clarify_assets/__init__.py
clarify_assets/__utils__/__init__.py
clarify_assets/__utils__/copy.py
clarify_assets/__utils__/parsers.py
clarify_assets/__utils__/printing.py
clarify_assets/__utils__/validators.py
clarify_assets/broker/__init__.py
clarify_assets/broker/broker.py
clarify_assets/models/__init__.py
clarify_assets/models/asset.py
clarify_assets/models/attribute.py
clarify_assets-0.0.10.dist-info/LICENSE
clarify_assets-0.0.10.dist-info/METADATA
clarify_assets-0.0.10.dist-info/WHEEL
clarify_assets-0.0.10.dist-info/top_level.txt
clarify_assets-0.0.10.dist-info/RECORD
