Metadata-Version: 2.1
Name: clarify-assets
Version: 0.0.10
Summary: Populate Clarify metadata through asset models.
Home-page: https://github.com/clarify/clarify-assets
Author: Odd Gunnar Aspaas
Author-email: odd.gunnar@clarify.io
Project-URL: Bug Tracker, https://github.com/clarify/clarify-assets/issues
Classifier: Programming Language :: Python :: 3
Classifier: License :: OSI Approved :: MIT License
Classifier: Operating System :: OS Independent
Requires-Python: >=3.10
License-File: LICENSE
Requires-Dist: requests
Requires-Dist: pyclarify
Requires-Dist: tqdm
